docquery/__init__.py
docquery/config.py
docquery/document.py
docquery/find_leaf_nodes.js
docquery/ocr_reader.py
docquery/transformers_patch.py
docquery/version.py
docquery/web.py
docquery/cmd/__init__.py
docquery/cmd/__main__.py
docquery/cmd/scan.py
docquery/ext/__init__.py
docquery/ext/functools.py
docquery/ext/itertools.py
docquery/ext/model.py
docquery/ext/pipeline_document_classification.py
docquery/ext/pipeline_document_question_answering.py
docquery/ext/qa_helpers.py
docquery-0.0.7.dist-info/LICENSE
docquery-0.0.7.dist-info/METADATA
docquery-0.0.7.dist-info/WHEEL
docquery-0.0.7.dist-info/entry_points.txt
docquery-0.0.7.dist-info/top_level.txt
docquery-0.0.7.dist-info/RECORD
